mqttsn/__init__.py
mqttsn/client.py
mqttsn/internal.py
mqttsn/lib/__init__.py
mqttsn/lib/advertises.py
mqttsn/lib/connects.py
mqttsn/lib/disconnects.py
mqttsn/lib/flags.py
mqttsn/lib/gw.py
mqttsn/lib/helpers.py
mqttsn/lib/message_headers.py
mqttsn/lib/names.py
mqttsn/lib/objects.py
mqttsn/lib/packets.py
mqttsn/lib/ping.py
mqttsn/lib/publishes.py
mqttsn/lib/registers.py
mqttsn/lib/subscribes.py
mqttsn/lib/unsubscribes.py
mqttsn/lib/will.py
mqttsn-0.0.4.dist-info/METADATA
mqttsn-0.0.4.dist-info/RECORD
mqttsn-0.0.4.dist-info/WHEEL
mqttsn-0.0.4.dist-info/top_level.txt
