Metadata-Version: 2.1
Name: mqttsn
Version: 0.0.4
Summary: Python client based on Eclipse RSMB client for MQTT-SN brokers
Home-page: https://github.com/luanguimaraesla/mqttsn
Author: Luan Guimarães Lacerda
Author-email: luan@live.in
License: MIT License
Keywords: iot,mosquitto,mqtt,mqttsn,mqtt-sn,message,queue,pipeline,sensors,network,udp,protocol
Platform: UNKNOWN
Classifier: Development Status :: 3 - Alpha
Classifier: Intended Audience :: Developers
Classifier: Operating System :: POSIX
Classifier: Programming Language :: Python
Classifier: Programming Language :: Python :: 3.6
Classifier: Topic :: Software Development :: Libraries
Provides-Extra: docs
Provides-Extra: dev
Requires-Dist: paho-mqtt
Provides-Extra: dev
Requires-Dist: pytest; extra == 'dev'
Requires-Dist: pytest-cov; extra == 'dev'
Requires-Dist: coverage; extra == 'dev'
Requires-Dist: flake8; extra == 'dev'
Requires-Dist: bumpversion; extra == 'dev'
Provides-Extra: docs
Requires-Dist: docutils; extra == 'docs'
Requires-Dist: sphinx-autobuild; extra == 'docs'
